mathraining/scrapper/__init__.py
mathraining/scrapper/mathsite.py
mathraining/scrapper/mathuser.py
mathraining_scrapper-0.0.4.dist-info/LICENSE
mathraining_scrapper-0.0.4.dist-info/METADATA
mathraining_scrapper-0.0.4.dist-info/WHEEL
mathraining_scrapper-0.0.4.dist-info/top_level.txt
mathraining_scrapper-0.0.4.dist-info/RECORD
