Metadata-Version: 2.1
Name: mathraining-scrapper
Version: 0.0.4
Summary: The Mathraining Website Scrapper
Home-page: https://github.com/Mathraining-Discord-Bot/MT-Scrapper
Author: Charlotte Thomas
Author-email: charlotte@sfiars.eu
License: UNKNOWN
Platform: UNKNOWN
Classifier: Development Status :: 3 - Alpha
Classifier: License :: OSI Approved :: GNU General Public License v3 (GPLv3)
Classifier: Programming Language :: Python :: 3
Classifier: Programming Language :: Python :: 3.4
Classifier: Programming Language :: Python :: 3.5
Classifier: Programming Language :: Python :: 3.6
Requires-Python: >=3.5
Requires-Dist: faster-than-requests
Requires-Dist: beautifulsoup4
